{
  "db_name": "PostgreSQL",
  "query": "\n        select course_id, tutor_id, course_name, posted_time\n        from courses_c4\n        where course_id = $1",
  "describe": {
    "columns": [
      {
        "ordinal": 0,
        "name": "course_id",
        "type_info": "Int4"
      },
      {
        "ordinal": 1,
        "name": "tutor_id",
        "type_info": "Int4"
      },
      {
        "ordinal": 2,
        "name": "course_name",
        "type_info": "Varchar"
      },
      {
        "ordinal": 3,
        "name": "posted_time",
        "type_info": "Timestamp"
      }
    ],
    "parameters": {
      "Left": [
        "Int4"
      ]
    },
    "nullable": [
      false,
      false,
      false,
      true
    ]
  },
  "hash": "4f948d92472cbece46022645f6180c626feb869a9b56a157b15c3225358f3047"
}
